ddm_flow_scripts/__init__.py
ddm_flow_scripts/csv_organizer.py
ddm_flow_scripts/multisheet_fov_aggregator.py
ddm_flow_scripts/plotter.py
ddm_flow-0.1.1.dist-info/METADATA
ddm_flow-0.1.1.dist-info/WHEEL
ddm_flow-0.1.1.dist-info/entry_points.txt
ddm_flow-0.1.1.dist-info/top_level.txt
ddm_flow-0.1.1.dist-info/RECORD
